MANIFEST.in
README.md
setup.cfg
setup.py
bin/__init__.py
bin/ai_check.py
bin/ai_env.py
bin/ai_init.py
bin/ai_pkg.py
bin/be_init.py
bin/be_pkg.py
bin/generate_activate_code.py
core/__init__.py
core/main.py
pypi_django_cli.egg-info/PKG-INFO
pypi_django_cli.egg-info/SOURCES.txt
pypi_django_cli.egg-info/dependency_links.txt
pypi_django_cli.egg-info/entry_points.txt
pypi_django_cli.egg-info/requires.txt
pypi_django_cli.egg-info/top_level.txt